dict_path_finder/__init__.py
dict_path_finder/main.py
dict_path_finder-0.0.3.dist-info/METADATA
dict_path_finder-0.0.3.dist-info/WHEEL
dict_path_finder-0.0.3.dist-info/top_level.txt
dict_path_finder-0.0.3.dist-info/RECORD
