Metadata-Version: 2.1
Name: dict-path-finder
Version: 0.0.3
Summary: Find dictionary path by key and value
Home-page: https://github.com/developers-dev/
Author: Jinhan Kim
Author-email: developers.xyz@gmail.com
Classifier: Programming Language :: Python :: 3
Classifier: Programming Language :: Python :: 2
Classifier: License :: OSI Approved :: MIT License
Classifier: Operating System :: OS Independent
